<?xml version="1.0" encoding="UTF-8"?><record_update sys_domain="global" table="par_dashboard_tab">
    <par_dashboard_tab action="INSERT_OR_UPDATE">
        <active>true</active>
        <background_color/>
        <dashboard display_value="Document Approvals">247590fb9f008610773ed123ef909254</dashboard>
        <name>Tab</name>
        <order>0</order>
        <sys_class_name>par_dashboard_tab</sys_class_name>
        <sys_created_by>sarathy.rambha.snf.us@snc</sys_created_by>
        <sys_created_on>2024-02-05 21:38:58</sys_created_on>
        <sys_domain>global</sys_domain>
        <sys_domain_path>/</sys_domain_path>
        <sys_id>e47590fbe3008610b4a781580ea4b454</sys_id>
        <sys_mod_count>0</sys_mod_count>
        <sys_name>Tab</sys_name>
        <sys_overrides/>
        <sys_package display_value="WDocApp" source="x_snc_wdocapp">447550fb7f008610112a32e1fa1d7078</sys_package>
        <sys_policy/>
        <sys_scope display_value="WDocApp">447550fb7f008610112a32e1fa1d7078</sys_scope>
        <sys_update_name>par_dashboard_tab_e47590fbe3008610b4a781580ea4b454</sys_update_name>
        <sys_updated_by>sarathy.rambha.snf.us@snc</sys_updated_by>
        <sys_updated_on>2024-02-05 21:38:58</sys_updated_on>
    </par_dashboard_tab>
</record_update>
